{
  "species_id": "tagame",
  "species_ja": "タガメ",
  "scientific_name": "Kirkaldyia deyrolli",
  "credit_line": "Wikimedia Commons",
  "creator": "Ffish.asia",
  "fetched_date": "2026-06-21",
  "specimen": {
    "institution": "Wikimedia Commons",
    "institutionCode": "WMC",
    "collectionCode": null,
    "catalogNumber": "File:Tagame-3D-VR-thumb.jpg",
    "occurrenceId": "https://commons.wikimedia.org/wiki/File:Tagame-3D-VR-thumb.jpg",
    "persistentId": "https://commons.wikimedia.org/wiki/File:Tagame-3D-VR-thumb.jpg",
    "basisOfRecord": "HumanObservation",
    "typeStatus": null,
    "sex": null,
    "lifeStage": null,
    "recordedBy": "Ffish.asia",
    "eventDate": "2020-08-01",
    "eventYear": 2020,
    "country": null,
    "localityVerbatim": "タガメ（メス、熊本県球磨郡）の３D・VRモデル",
    "localityNormalized": "タガメ（メス、熊本県球磨郡）の３D・VRモデル",
    "preparations": null
  },
  "source": {
    "gbifOccurrenceKey": null,
    "institutionRecordUrl": "https://commons.wikimedia.org/wiki/File:Tagame-3D-VR-thumb.jpg",
    "sourceMediaUrl": "https://upload.wikimedia.org/wikipedia/commons/e/ec/Tagame-3D-VR-thumb.jpg",
    "datasetKey": null,
    "metadataLicense": "CC0-1.0",
    "mediaLicense": "CC0-1.0",
    "licenseUrl": "http://creativecommons.org/publicdomain/zero/1.0/deed.en"
  },
  "files": {
    "original": "original/WMCFileTagame3DVRthumbjpg_original.jpg",
    "segmented": "processed/WMCFileTagame3DVRthumbjpg_L1_segmented.png",
    "display": "processed/WMCFileTagame3DVRthumbjpg_L2_grade.webp",
    "thumbnails": {
      "54": "thumb/WMCFileTagame3DVRthumbjpg_54.webp",
      "108": "thumb/WMCFileTagame3DVRthumbjpg_108.webp",
      "216": "thumb/WMCFileTagame3DVRthumbjpg_216.webp"
    }
  },
  "original_sha256": "d5ef9368ddbd0807c09c2d61033f9c810f1b13dffda511314feac54d6bf9fec1",
  "processing": {
    "cropBox": [
      23,
      106,
      645,
      468
    ],
    "rotationDegrees": 0,
    "padding": 0.1,
    "canvas": 512,
    "minSize": 20,
    "bgMethod": "birefnet-general",
    "segmentationModel": "BiRefNet",
    "modelVersion": "rembg-2.0.67",
    "colorGradeVersion": "q4b-l2-v1",
    "manualMaskCorrection": false
  },
  "modifications": [
    "cropped",
    "background removed",
    "color adjusted"
  ],
  "raw": {
    "originalImage": "original/WMCFileTagame3DVRthumbjpg_original.jpg",
    "verbatimLabelText": null,
    "sourceRecordSnapshot": null
  },
  "notes": "butterfly dorsal — head up by convention, no rotation"
}